tendril/__init__.py
tendril/config/__init__.py
tendril/config/influxdb.py
tendril/config/influxdb_buckets.py
tendril/connectors/__init__.py
tendril/connectors/influxdb/__init__.py
tendril/connectors/influxdb/aio.py
tendril/connectors/influxdb/tx.py
tendril/connectors/influxdb/query/__init__.py
tendril/connectors/influxdb/query/builder.py
tendril/connectors/influxdb/query/planner.py
tendril/connectors/influxdb/query/schema.py
tendril/core/__init__.py
tendril/core/tsdb/__init__.py
tendril/core/tsdb/aio.py
tendril/core/tsdb/constants.py
tendril/core/tsdb/tx.py
tendril/core/tsdb/query/__init__.py
tendril/core/tsdb/query/models.py
tendril/core/tsdb/query/planner.py
tendril_connector_influxdb-0.4.1.dist-info/LICENSE
tendril_connector_influxdb-0.4.1.dist-info/METADATA
tendril_connector_influxdb-0.4.1.dist-info/WHEEL
tendril_connector_influxdb-0.4.1.dist-info/top_level.txt
tendril_connector_influxdb-0.4.1.dist-info/RECORD
